fc/__init__.py
fc/client.py
fc/exceptions.py
tests/__init__.py
tests/test_client.py
funchodata-1.0.1.dist-info/LICENSE
funchodata-1.0.1.dist-info/METADATA
funchodata-1.0.1.dist-info/WHEEL
funchodata-1.0.1.dist-info/top_level.txt
funchodata-1.0.1.dist-info/RECORD
